devtools_js_minifier/__init__.py
devtools_js_minifier-1.0.1.dist-info/METADATA
devtools_js_minifier-1.0.1.dist-info/WHEEL
devtools_js_minifier-1.0.1.dist-info/top_level.txt
devtools_js_minifier-1.0.1.dist-info/RECORD
