Metadata-Version: 2.1
Name: devtools_js_minifier
Version: 1.0.1
Summary: JavaScript minifier
Home-page: https://devtools.at/tools/js-minifier
Author: DevTools.at
Author-email: hello@devtools.at
Project-URL: Homepage, https://devtools.at/tools/js-minifier
Project-URL: Repository, https://github.com/devtools-at/js-minifier
Classifier: Development Status :: 4 - Beta
Classifier: Intended Audience :: Developers
Classifier: License :: OSI Approved :: MIT License
Classifier: Programming Language :: Python :: 3
Requires-Python: >=3.8
